docstring_parser/__init__.py
docstring_parser/common.py
docstring_parser/epydoc.py
docstring_parser/google.py
docstring_parser/numpydoc.py
docstring_parser/parser.py
docstring_parser/py.typed
docstring_parser/rest.py
docstring_parser/tests/__init__.py
docstring_parser/tests/_pydoctor.py
docstring_parser/tests/test_epydoc.py
docstring_parser/tests/test_google.py
docstring_parser/tests/test_numpydoc.py
docstring_parser/tests/test_parser.py
docstring_parser/tests/test_rest.py
docstring_parser/tests/test_util.py
docstring_parser/util.py
docstring_parser-0.14.dist-info/LICENSE.md
docstring_parser-0.14.dist-info/WHEEL
docstring_parser-0.14.dist-info/METADATA
docstring_parser-0.14.dist-info/RECORD
