Metadata-Version: 2.1
Name: docstring-parser
Version: 0.14
Summary: Parse Python docstrings in reST, Google and Numpydoc format
Home-page: https://github.com/rr-/docstring_parser
License: MIT
Author: Marcin Kurczewski
Author-email: dash@wind.garden
Requires-Python: >=3.6,<4.0
Classifier: Development Status :: 4 - Beta
Classifier: Environment :: Other Environment
Classifier: Intended Audience :: Developers
Classifier: License :: OSI Approved :: MIT License
Classifier: Natural Language :: English
Classifier: Operating System :: OS Independent
Classifier: Programming Language :: Python :: 3
Classifier: Programming Language :: Python :: 3.10
Classifier: Programming Language :: Python :: 3.6
Classifier: Programming Language :: Python :: 3.7
Classifier: Programming Language :: Python :: 3.8
Classifier: Programming Language :: Python :: 3.9
Classifier: Topic :: Documentation :: Sphinx
Classifier: Topic :: Software Development :: Libraries :: Python Modules
Classifier: Topic :: Text Processing :: Markup
Project-URL: Repository, https://github.com/rr-/docstring_parser
